tfx_bsl/__init__.py
tfx_bsl/types_compat.py
tfx_bsl/version.py
tfx_bsl/arrow/__init__.py
tfx_bsl/arrow/array_util.py
tfx_bsl/arrow/array_util_test.py
tfx_bsl/arrow/path.py
tfx_bsl/arrow/sql_util.py
tfx_bsl/arrow/sql_util_test.py
tfx_bsl/arrow/table_util.py
tfx_bsl/arrow/table_util_test.py
tfx_bsl/beam/__init__.py
tfx_bsl/beam/pickle_helpers.py
tfx_bsl/beam/run_inference.py
tfx_bsl/beam/test_helpers.py
tfx_bsl/cc/__init__.py
tfx_bsl/cc/tfx_bsl_extension.so
tfx_bsl/coders/__init__.py
tfx_bsl/coders/batch_util.py
tfx_bsl/coders/batch_util_test.py
tfx_bsl/coders/csv_decoder.py
tfx_bsl/coders/csv_decoder_test.py
tfx_bsl/coders/example_coder.py
tfx_bsl/coders/example_coder_test.py
tfx_bsl/coders/example_numpy_decoder_test.py
tfx_bsl/coders/sequence_example_coder.py
tfx_bsl/coders/sequence_example_coder_test.py
tfx_bsl/coders/tf_graph_record_decoder.py
tfx_bsl/coders/tf_graph_record_decoder_test.py
tfx_bsl/public/__init__.py
tfx_bsl/public/beam/__init__.py
tfx_bsl/public/beam/run_inference.py
tfx_bsl/public/proto/__init__.py
tfx_bsl/public/proto/model_spec_pb2.py
tfx_bsl/public/proto/slicing_spec_pb2.py
tfx_bsl/public/tfxio/__init__.py
tfx_bsl/public/tfxio/tfxio_import_test.py
tfx_bsl/sketches/__init__.py
tfx_bsl/sketches/kmv_sketch_test.py
tfx_bsl/sketches/misragries_sketch_test.py
tfx_bsl/sketches/quantiles_sketch_test.py
tfx_bsl/statistics/__init__.py
tfx_bsl/statistics/merge_util.py
tfx_bsl/statistics/merge_util_test.py
tfx_bsl/statistics/sql_util.py
tfx_bsl/statistics/sql_util_test.py
tfx_bsl/telemetry/__init__.py
tfx_bsl/telemetry/collection.py
tfx_bsl/telemetry/collection_test.py
tfx_bsl/telemetry/util.py
tfx_bsl/telemetry/util_test.py
tfx_bsl/test_util/__init__.py
tfx_bsl/test_util/run_all_tests.py
tfx_bsl/tfxio/__init__.py
tfx_bsl/tfxio/csv_tfxio.py
tfx_bsl/tfxio/csv_tfxio_test.py
tfx_bsl/tfxio/dataset_options.py
tfx_bsl/tfxio/dataset_tfxio.py
tfx_bsl/tfxio/dataset_tfxio_test.py
tfx_bsl-1.17.1.dist-info/METADATA
tfx_bsl-1.17.1.dist-info/WHEEL
tfx_bsl-1.17.1.dist-info/namespace_packages.txt
tfx_bsl-1.17.1.dist-info/top_level.txt
tfx_bsl-1.17.1.dist-info/RECORD
tfx_bsl-1.17.1.dist-info/licenses/LICENSE
