Metadata-Version: 2.4
Name: tfx-bsl
Version: 1.17.1
Summary: tfx_bsl (TFX Basic Shared Libraries) contains libraries shared by many TFX (TensorFlow eXtended) libraries and components.
Home-page: https://www.tensorflow.org/tfx
Download-URL: https://github.com/tensorflow/tfx-bsl/tags
Author: Google LLC
Author-email: tensorflow-extended-dev@googlegroups.com
License: Apache 2.0
Keywords: tfx bsl
Classifier: Development Status :: 5 - Production/Stable
Classifier: Intended Audience :: Developers
Classifier: Intended Audience :: Education
Classifier: Intended Audience :: Science/Research
Classifier: License :: OSI Approved :: Apache Software License
Classifier: Operating System :: MacOS :: MacOS X
Classifier: Operating System :: POSIX :: Linux
Classifier: Programming Language :: Python
Classifier: Programming Language :: Python :: 3
Classifier: Programming Language :: Python :: 3.9
Classifier: Programming Language :: Python :: 3.10
Classifier: Programming Language :: Python :: 3.11
Classifier: Programming Language :: Python :: 3 :: Only
Classifier: Topic :: Scientific/Engineering
Classifier: Topic :: Scientific/Engineering :: Artificial Intelligence
Classifier: Topic :: Scientific/Engineering :: Mathematics
Classifier: Topic :: Software Development
Classifier: Topic :: Software Development :: Libraries
Classifier: Topic :: Software Development :: Libraries :: Python Modules
Requires-Python: >=3.9,<4
License-File: LICENSE
Requires-Dist: absl-py<2.0.0,>=0.9
Requires-Dist: apache-beam[gcp]<3,>=2.53; python_version >= "3.11"
Requires-Dist: apache-beam[gcp]<2.51,>=2.50; python_version < "3.11"
Requires-Dist: google-api-python-client<2,>=1.7.11
Requires-Dist: numpy>=1.22.0
Requires-Dist: pandas<2,>=1.0
Requires-Dist: protobuf<6.0.0,>=4.25.2; python_version >= "3.11"
Requires-Dist: protobuf<6.0.0,>=4.21.6; python_version < "3.11"
Requires-Dist: pyarrow<11,>=10
Requires-Dist: tensorflow<2.18,>=2.17
Requires-Dist: tensorflow-metadata<1.18.0,>=1.17.1
Requires-Dist: tensorflow-serving-api<3,>=2.13.0
Dynamic: author
Dynamic: author-email
Dynamic: classifier
Dynamic: description
Dynamic: description-content-type
Dynamic: download-url
Dynamic: home-page
Dynamic: keywords
Dynamic: license
Dynamic: license-file
Dynamic: requires-dist
Dynamic: requires-python
Dynamic: summary
